jaxpme/__init__.py
jax_pme-0.0.0.dist-info/METADATA
jax_pme-0.0.0.dist-info/WHEEL
jax_pme-0.0.0.dist-info/RECORD
