Metadata-Version: 2.1
Name: jax-pme
Version: 0.0.0
Summary: (Particle Mesh) Ewald summation in JAX
License: MIT
Author: Marcel Langer
Author-email: dev@marcel.science
Requires-Python: >=3.7
Classifier: License :: OSI Approved :: MIT License
Classifier: Programming Language :: Python :: 3
Classifier: Programming Language :: Python :: 3.7
Classifier: Programming Language :: Python :: 3.8
Classifier: Programming Language :: Python :: 3.9
Classifier: Programming Language :: Python :: 3.10
Classifier: Programming Language :: Python :: 3.11
Classifier: Programming Language :: Python :: 3.12
Classifier: Programming Language :: Python :: 3.13
